nacc/__init__.py
nacc/redcap2nacc.py
nacc/uds2/__init__.py
nacc/uds2/ivp/__init__.py
nacc/uds2/ivp/forms.py
nacc/uds3/__init__.py
nacc/uds3/blanks.py
nacc/uds3/clsform.py
nacc/uds3/filters.py
nacc/uds3/packet.py
nacc/uds3/fvp/__init__.py
nacc/uds3/fvp/builder.py
nacc/uds3/fvp/forms.py
nacc/uds3/ivp/__init__.py
nacc/uds3/ivp/builder.py
nacc/uds3/ivp/forms.py
nacc/uds3/np/__init__.py
nacc/uds3/np/builder.py
nacc/uds3/np/forms.py
nacculator-0.6.1.dist-info/AUTHORS
nacculator-0.6.1.dist-info/LICENSE
nacculator-0.6.1.dist-info/METADATA
nacculator-0.6.1.dist-info/WHEEL
nacculator-0.6.1.dist-info/entry_points.txt
nacculator-0.6.1.dist-info/top_level.txt
nacculator-0.6.1.dist-info/RECORD
