Metadata-Version: 2.1
Name: nacculator
Version: 0.6.1
Summary: CSV to NACC's UDS3 format converter
Home-page: https://github.com/ctsit/nacculator
Author: Taeber Rapczak
Author-email: taeber@ufl.edu
Maintainer: UF CTS-IT
Maintainer-email: ctsit@ctsi.ufl.edu
License: BSD 2-Clause
Download-URL: https://github.com/ctsit/nacculator/releases/tag/0.6.1
Keywords: REDCap,NACC,UDS,Clinical data
Platform: UNKNOWN
